tailwind_for_django/__init__.py
tailwind_for_django/management/__init__.py
tailwind_for_django/management/commands/__init__.py
tailwind_for_django/management/commands/setup_tailwind.py
tailwind_for_django-0.1.7.dist-info/LICENSE
tailwind_for_django-0.1.7.dist-info/METADATA
tailwind_for_django-0.1.7.dist-info/WHEEL
tailwind_for_django-0.1.7.dist-info/top_level.txt
tailwind_for_django-0.1.7.dist-info/RECORD
