Metadata-Version: 2.1
Name: tailwind-for-django
Version: 0.1.7
Summary: A library for easy setup of tailwind in django project
Home-page: https://github.com/AndreaGallini/tailwind_for_django
Author: Andrea Gallini
Author-email: tuo_email@example.com
License: MIT License
Platform: UNKNOWN
Classifier: Environment :: Web Environment
Classifier: Framework :: Django
Classifier: Framework :: Django :: 3.2
Classifier: Intended Audience :: Developers
Classifier: License :: OSI Approved :: MIT License
Classifier: Operating System :: OS Independent
Classifier: Programming Language :: Python
Classifier: Programming Language :: Python :: 3
Classifier: Topic :: Software Development :: Build Tools
License-File: LICENSE
Requires-Dist: Django (>=3.2)
